hdcms_bindings.cpython-39-darwin.so
hdcms_bindings-0.1.6.dist-info/LICENSE
hdcms_bindings-0.1.6.dist-info/METADATA
hdcms_bindings-0.1.6.dist-info/WHEEL
hdcms_bindings-0.1.6.dist-info/top_level.txt
hdcms_bindings-0.1.6.dist-info/RECORD
