Metadata-Version: 2.1
Name: hdcms-bindings
Version: 0.1.6
Summary: This package wraps the C functions in hdcms
Author: Arun Moorthy
Author-email: Jason Eveleth <hdcms@jasoneveleth.com>
License: NIST-developed software is provided by NIST as a public service. You may use,
Project-URL: Homepage, https://github.com/jasoneveleth/hdcms-bindings
Project-URL: Bug Tracker, https://github.com/jasoneveleth/hdcms-bindings/issues
Requires-Python: >=3.7
License-File: LICENSE
